[
 {
   "ATK": 2,
   "ACC": 10,
   "CRC": 10,
   "PEN": 10,
   "HP": 3,
   "DEF": 1,
   "DOG": 15,
   "SPD": 2
 },
 {
   "ATK": 4,
   "ACC": 20,
   "CRC": 15,
   "PEN": 15,
   "HP": 6,
   "DEF": 2,
   "DOG": 30,
   "SPD": 5
 },
 {
   "ATK": 8,
   "ACC": 40,
   "CRC": 20,
   "PEN": 20,
   "HP": 12,
   "DEF": 4,
   "DOG": 60,
   "SPD": 9
 },
 {
   "ATK": 16,
   "ACC": 70,
   "CRC": 25,
   "PEN": 25,
   "HP": 24,
   "DEF": 8,
   "DOG": 100,
   "SPD": 14
 },
 {
   "ATK": 32,
   "ACC": 100,
   "CRC": 30,
   "PEN": 30,
   "HP": 48,
   "DEF": 16,
   "DOG": 150,
   "SPD": 20
 },
 {
   "ATK": 64,
   "ACC": 140,
   "CRC": 35,
   "PEN": 35,
   "HP": 96,
   "DEF": 32,
   "DOG": 200,
   "SPD": 25
 }
]